walt/__init__.py
walt/base.html
walt/main.html
walt/mkdocs_theme.yml
walt/walt.min.css
walt/highlightjs/catppuccin-latte.min.css
walt/highlightjs/catppuccin-macchiato.min.css
walt/highlightjs/highlight.min.js
mkdocs_walt-0.1.1.dist-info/METADATA
mkdocs_walt-0.1.1.dist-info/WHEEL
mkdocs_walt-0.1.1.dist-info/entry_points.txt
mkdocs_walt-0.1.1.dist-info/top_level.txt
mkdocs_walt-0.1.1.dist-info/RECORD
