Metadata-Version: 2.1
Name: mkdocs-walt
Version: 0.1.1
Summary: A minimal theme for MkDocs
Home-page: https://github.com/codesue/walt
Author: Suzen Fylke
Author-email: codesue@users.noreply.github.com
License: MIT
Keywords: mkdocs,mkdocs-theme,walt
Classifier: License :: OSI Approved :: MIT License
Classifier: Programming Language :: Python
Classifier: Programming Language :: Python :: 3
Requires-Dist: mkdocs
